{
    "/installer/js/app.js": "/installer/js/app.js",
    "/js/app.js": "/js/app.js",
    "/css/app.css": "/css/app.css",
    "/installer/css/app.css": "/installer/css/app.css",
    "/js/chunks/2076a31b6effc49f0838.js": "/js/chunks/2076a31b6effc49f0838.js",
    "/js/chunks/de3ba423bfb67f99ea4a.js": "/js/chunks/de3ba423bfb67f99ea4a.js",
    "/js/chunks/cb9c552420855c67bf83.js": "/js/chunks/cb9c552420855c67bf83.js",
    "/js/chunks/184a5d9480503c3bad30.js": "/js/chunks/184a5d9480503c3bad30.js",
    "/js/chunks/5b31a534f8e9e2c45d8a.js": "/js/chunks/5b31a534f8e9e2c45d8a.js",
    "/js/chunks/af14cbc496f83d8e62fa.js": "/js/chunks/af14cbc496f83d8e62fa.js",
    "/js/chunks/bd641d5cf477acd1f345.js": "/js/chunks/bd641d5cf477acd1f345.js",
    "/js/chunks/1fdcd6f8359b7aaf5e34.js": "/js/chunks/1fdcd6f8359b7aaf5e34.js",
    "/js/chunks/d7a8c324a16d763ba4e4.js": "/js/chunks/d7a8c324a16d763ba4e4.js",
    "/js/chunks/558a359a79a584810b4a.js": "/js/chunks/558a359a79a584810b4a.js",
    "/js/chunks/4183239f5aa3df45ba9f.js": "/js/chunks/4183239f5aa3df45ba9f.js",
    "/js/chunks/dcc79b1e9b7f3d0a3bc0.js": "/js/chunks/dcc79b1e9b7f3d0a3bc0.js",
    "/js/chunks/bbfd4799a9bb91f816a9.js": "/js/chunks/bbfd4799a9bb91f816a9.js",
    "/js/chunks/d7372c4471043fa032c3.js": "/js/chunks/d7372c4471043fa032c3.js",
    "/js/chunks/20520b14338b5afdaca5.js": "/js/chunks/20520b14338b5afdaca5.js",
    "/js/chunks/b5ff04dfab8a1b706269.js": "/js/chunks/b5ff04dfab8a1b706269.js",
    "/js/chunks/95419d483843c7510f93.js": "/js/chunks/95419d483843c7510f93.js",
    "/js/chunks/bd7e10ce1eb75a8d3601.js": "/js/chunks/bd7e10ce1eb75a8d3601.js",
    "/js/chunks/99d22d9106d1a261a418.js": "/js/chunks/99d22d9106d1a261a418.js",
    "/js/chunks/1bce2ba0a078c722e8e1.js": "/js/chunks/1bce2ba0a078c722e8e1.js",
    "/js/chunks/69d389d616418cdc02e2.js": "/js/chunks/69d389d616418cdc02e2.js",
    "/js/chunks/7f15176b01beb33a7916.js": "/js/chunks/7f15176b01beb33a7916.js",
    "/js/chunks/f1852820ce460fb6d854.js": "/js/chunks/f1852820ce460fb6d854.js",
    "/js/chunks/d5793363d2eafb7f8c3d.js": "/js/chunks/d5793363d2eafb7f8c3d.js",
    "/js/chunks/206ddf17fcea22a597f0.js": "/js/chunks/206ddf17fcea22a597f0.js",
    "/js/chunks/23e66ca11059e5197a99.js": "/js/chunks/23e66ca11059e5197a99.js",
    "/js/chunks/c53cc4d76d83cdf28ea1.js": "/js/chunks/c53cc4d76d83cdf28ea1.js",
    "/js/chunks/fd986862c3e3e88996d5.js": "/js/chunks/fd986862c3e3e88996d5.js",
    "/js/chunks/2655b8d1510fa089855a.js": "/js/chunks/2655b8d1510fa089855a.js",
    "/js/chunks/c07860d42b7b61cf653b.js": "/js/chunks/c07860d42b7b61cf653b.js",
    "/js/chunks/dc0549b87d6c8f954169.js": "/js/chunks/dc0549b87d6c8f954169.js",
    "/js/chunks/0ddc195503986f86d6ac.js": "/js/chunks/0ddc195503986f86d6ac.js",
    "/js/chunks/9f2ea91dfdd11a464988.js": "/js/chunks/9f2ea91dfdd11a464988.js",
    "/js/chunks/8f1073d1359dd0578eee.js": "/js/chunks/8f1073d1359dd0578eee.js",
    "/js/chunks/e9e8978e63f04c0f8275.js": "/js/chunks/e9e8978e63f04c0f8275.js",
    "/js/chunks/5bfb0e45e67c6214ad51.js": "/js/chunks/5bfb0e45e67c6214ad51.js",
    "/js/chunks/2c86cc92287aa316d640.js": "/js/chunks/2c86cc92287aa316d640.js",
    "/js/chunks/89d355f4f99a99dfac18.js": "/js/chunks/89d355f4f99a99dfac18.js",
    "/js/chunks/4469c2b968974a851459.js": "/js/chunks/4469c2b968974a851459.js",
    "/js/chunks/f34f3926758f24051fd8.js": "/js/chunks/f34f3926758f24051fd8.js",
    "/js/chunks/0bf6e51294e9332887f1.js": "/js/chunks/0bf6e51294e9332887f1.js",
    "/js/chunks/f82cb89689da24251515.js": "/js/chunks/f82cb89689da24251515.js",
    "/js/chunks/dd0780348e80c800bade.js": "/js/chunks/dd0780348e80c800bade.js",
    "/js/chunks/5fb92d5c3dfe6d677128.js": "/js/chunks/5fb92d5c3dfe6d677128.js",
    "/js/chunks/cd1fb85a0bab5d25277f.js": "/js/chunks/cd1fb85a0bab5d25277f.js",
    "/js/chunks/d10e4110e4d15cceff91.js": "/js/chunks/d10e4110e4d15cceff91.js",
    "/js/chunks/901c1a6679f483cb6824.js": "/js/chunks/901c1a6679f483cb6824.js",
    "/js/chunks/7fe440ac820a24009553.js": "/js/chunks/7fe440ac820a24009553.js",
    "/js/chunks/8750b922107cc02f1bd1.js": "/js/chunks/8750b922107cc02f1bd1.js",
    "/js/chunks/b03b01081371ec83d238.js": "/js/chunks/b03b01081371ec83d238.js",
    "/js/chunks/8451ede2ac09f069b3aa.js": "/js/chunks/8451ede2ac09f069b3aa.js",
    "/js/chunks/98c913f131353a6d6ab9.js": "/js/chunks/98c913f131353a6d6ab9.js",
    "/js/chunks/b7f9af75b26cba8a6482.js": "/js/chunks/b7f9af75b26cba8a6482.js"
}
